{
    "version": 1,
    "graph_name": "ogbn-products",
    "train_mode": "full",
    "cpu_model": "Intel(R) Xeon(R) Gold 6240 CPU @ 2.60GHz",
    "num_node": 2449029,
    "num_edge": 126167309,
    "feat_width": 100,
    "num_epoch": 100,
    "num_partition": 1,
    "weight_decay": 0.0,
    "learning_rate": 0.002,
    "dropout": 0.3,
    "test_acc": 0.7422528038837988,
    "results": [
        {
            "epoch": 0,
            "eval_acc": 0.3083437174172876,
            "forward_time": 26.537461042404175,
            "backward_time": 38.38983607292175,
            "cur_epoch_time": 64.92731642723083,
            "acc_epoch_time": 64.92731642723083,
            "evaluate_time": 23.38145112991333,
            "loss": 8.896957397460938
        },
        {
            "epoch": 1,
            "eval_acc": 0.10779950665005213,
            "forward_time": 27.981279611587524,
            "backward_time": 29.263920307159424,
            "cur_epoch_time": 57.24527382850647,
            "acc_epoch_time": 122.1725902557373,
            "evaluate_time": 22.53521752357483,
            "loss": 23.801780700683594
        },
        {
            "epoch": 2,
            "eval_acc": 0.22132085547898175,
            "forward_time": 27.320352792739868,
            "backward_time": 27.32642102241516,
            "cur_epoch_time": 54.64678621292114,
            "acc_epoch_time": 176.81937646865845,
            "evaluate_time": 22.646884441375732,
            "loss": 6.572160243988037
        },
        {
            "epoch": 3,
            "eval_acc": 0.19408488670752486,
            "forward_time": 27.363396167755127,
            "backward_time": 27.261756420135498,
            "cur_epoch_time": 54.62516403198242,
            "acc_epoch_time": 231.44454050064087,
            "evaluate_time": 22.774630784988403,
            "loss": 4.3237504959106445
        },
        {
            "epoch": 4,
            "eval_acc": 0.44281972382575086,
            "forward_time": 25.589815139770508,
            "backward_time": 26.75467324256897,
            "cur_epoch_time": 52.344499826431274,
            "acc_epoch_time": 283.78904032707214,
            "evaluate_time": 23.007949590682983,
            "loss": 3.3055567741394043
        },
        {
            "epoch": 5,
            "eval_acc": 0.3619255906212649,
            "forward_time": 26.632911443710327,
            "backward_time": 27.20408797264099,
            "cur_epoch_time": 53.83701038360596,
            "acc_epoch_time": 337.6260507106781,
            "evaluate_time": 22.903525590896606,
            "loss": 2.5789952278137207
        },
        {
            "epoch": 6,
            "eval_acc": 0.36215446430842,
            "forward_time": 27.323894023895264,
            "backward_time": 27.074192762374878,
            "cur_epoch_time": 54.39809799194336,
            "acc_epoch_time": 392.02414870262146,
            "evaluate_time": 22.934490203857422,
            "loss": 2.4247069358825684
        },
        {
            "epoch": 7,
            "eval_acc": 0.41049767311751395,
            "forward_time": 26.89272904396057,
            "backward_time": 26.683308124542236,
            "cur_epoch_time": 53.57604932785034,
            "acc_epoch_time": 445.6001980304718,
            "evaluate_time": 23.69051170349121,
            "loss": 2.360637664794922
        },
        {
            "epoch": 8,
            "eval_acc": 0.4353177529690003,
            "forward_time": 26.361764430999756,
            "backward_time": 26.71394681930542,
            "cur_epoch_time": 53.075719118118286,
            "acc_epoch_time": 498.6759171485901,
            "evaluate_time": 23.60892367362976,
            "loss": 2.269582986831665
        },
        {
            "epoch": 9,
            "eval_acc": 0.44701574142359435,
            "forward_time": 26.14800214767456,
            "backward_time": 26.552472352981567,
            "cur_epoch_time": 52.70048189163208,
            "acc_epoch_time": 551.3763990402222,
            "evaluate_time": 22.9771888256073,
            "loss": 2.1730475425720215
        },
        {
            "epoch": 10,
            "eval_acc": 0.47239529028812655,
            "forward_time": 26.888388872146606,
            "backward_time": 26.878025770187378,
            "cur_epoch_time": 53.76642155647278,
            "acc_epoch_time": 605.142820596695,
            "evaluate_time": 22.506362199783325,
            "loss": 2.037719964981079
        },
        {
            "epoch": 11,
            "eval_acc": 0.5104900439946087,
            "forward_time": 26.158541440963745,
            "backward_time": 26.094480276107788,
            "cur_epoch_time": 52.253032207489014,
            "acc_epoch_time": 657.395852804184,
            "evaluate_time": 23.273716688156128,
            "loss": 1.890323519706726
        },
        {
            "epoch": 12,
            "eval_acc": 0.5714467360069171,
            "forward_time": 26.317675352096558,
            "backward_time": 26.117156744003296,
            "cur_epoch_time": 52.43488550186157,
            "acc_epoch_time": 709.8307383060455,
            "evaluate_time": 23.29828691482544,
            "loss": 1.7782365083694458
        },
        {
            "epoch": 13,
            "eval_acc": 0.6284871449279048,
            "forward_time": 26.129822492599487,
            "backward_time": 26.425246953964233,
            "cur_epoch_time": 52.55507755279541,
            "acc_epoch_time": 762.3858158588409,
            "evaluate_time": 23.14483618736267,
            "loss": 1.6881977319717407
        },
        {
            "epoch": 14,
            "eval_acc": 0.6671667980571167,
            "forward_time": 26.451517343521118,
            "backward_time": 27.457515954971313,
            "cur_epoch_time": 53.90903997421265,
            "acc_epoch_time": 816.2948558330536,
            "evaluate_time": 23.103336811065674,
            "loss": 1.6134027242660522
        },
        {
            "epoch": 15,
            "eval_acc": 0.6812043842026295,
            "forward_time": 26.668411016464233,
            "backward_time": 26.446626663208008,
            "cur_epoch_time": 53.115044832229614,
            "acc_epoch_time": 869.4099006652832,
            "evaluate_time": 23.270781993865967,
            "loss": 1.5434999465942383
        },
        {
            "epoch": 16,
            "eval_acc": 0.6985987844264171,
            "forward_time": 27.61167287826538,
            "backward_time": 26.616748332977295,
            "cur_epoch_time": 54.22842836380005,
            "acc_epoch_time": 923.6383290290833,
            "evaluate_time": 22.60620880126953,
            "loss": 1.462731122970581
        },
        {
            "epoch": 17,
            "eval_acc": 0.7150268290822165,
            "forward_time": 27.87307119369507,
            "backward_time": 29.27097511291504,
            "cur_epoch_time": 57.14405393600464,
            "acc_epoch_time": 980.7823829650879,
            "evaluate_time": 23.004462242126465,
            "loss": 1.3808343410491943
        },
        {
            "epoch": 18,
            "eval_acc": 0.7313022912799125,
            "forward_time": 27.14836549758911,
            "backward_time": 27.170576572418213,
            "cur_epoch_time": 54.31899690628052,
            "acc_epoch_time": 1035.1013798713684,
            "evaluate_time": 23.173084020614624,
            "loss": 1.3140294551849365
        },
        {
            "epoch": 19,
            "eval_acc": 0.7436106095669202,
            "forward_time": 26.80860209465027,
            "backward_time": 26.569265842437744,
            "cur_epoch_time": 53.37787413597107,
            "acc_epoch_time": 1088.4792540073395,
            "evaluate_time": 23.028951406478882,
            "loss": 1.2491836547851562
        },
        {
            "epoch": 20,
            "eval_acc": 0.7511888716527223,
            "forward_time": 26.580416679382324,
            "backward_time": 26.825839042663574,
            "cur_epoch_time": 53.406261920928955,
            "acc_epoch_time": 1141.8855159282684,
            "evaluate_time": 23.212326526641846,
            "loss": 1.1866426467895508
        },
        {
            "epoch": 21,
            "eval_acc": 0.755334028431198,
            "forward_time": 26.460449695587158,
            "backward_time": 26.55612826347351,
            "cur_epoch_time": 53.01658487319946,
            "acc_epoch_time": 1194.902100801468,
            "evaluate_time": 22.93045401573181,
            "loss": 1.1397753953933716
        },
        {
            "epoch": 22,
            "eval_acc": 0.7632683162525749,
            "forward_time": 26.6331205368042,
            "backward_time": 27.081684827804565,
            "cur_epoch_time": 53.71481227874756,
            "acc_epoch_time": 1248.6169130802155,
            "evaluate_time": 22.833273887634277,
            "loss": 1.0991075038909912
        },
        {
            "epoch": 23,
            "eval_acc": 0.7712788953030033,
            "forward_time": 25.810954809188843,
            "backward_time": 26.54789686203003,
            "cur_epoch_time": 52.35885953903198,
            "acc_epoch_time": 1300.9757726192474,
            "evaluate_time": 22.961832761764526,
            "loss": 1.0625402927398682
        },
        {
            "epoch": 24,
            "eval_acc": 0.7767718637947257,
            "forward_time": 25.83477020263672,
            "backward_time": 26.915447235107422,
            "cur_epoch_time": 52.75026750564575,
            "acc_epoch_time": 1353.7260401248932,
            "evaluate_time": 23.937254905700684,
            "loss": 1.0220561027526855
        },
        {
            "epoch": 25,
            "eval_acc": 0.7801032474633166,
            "forward_time": 26.696573972702026,
            "backward_time": 26.775903940200806,
            "cur_epoch_time": 53.47248601913452,
            "acc_epoch_time": 1407.1985261440277,
            "evaluate_time": 23.392637014389038,
            "loss": 0.9847167730331421
        },
        {
            "epoch": 26,
            "eval_acc": 0.7834600615415914,
            "forward_time": 26.807671308517456,
            "backward_time": 26.387010097503662,
            "cur_epoch_time": 53.19468975067139,
            "acc_epoch_time": 1460.393215894699,
            "evaluate_time": 22.71276044845581,
            "loss": 0.9515419006347656
        },
        {
            "epoch": 27,
            "eval_acc": 0.7887241563461588,
            "forward_time": 27.1440851688385,
            "backward_time": 28.47814106941223,
            "cur_epoch_time": 55.62223434448242,
            "acc_epoch_time": 1516.0154502391815,
            "evaluate_time": 22.683091402053833,
            "loss": 0.9226953983306885
        },
        {
            "epoch": 28,
            "eval_acc": 0.7951834804058694,
            "forward_time": 25.750285863876343,
            "backward_time": 26.610971927642822,
            "cur_epoch_time": 52.36131405830383,
            "acc_epoch_time": 1568.3767642974854,
            "evaluate_time": 22.5593318939209,
            "loss": 0.8948776125907898
        },
        {
            "epoch": 29,
            "eval_acc": 0.8023548559367292,
            "forward_time": 25.594066858291626,
            "backward_time": 26.513105154037476,
            "cur_epoch_time": 52.10717988014221,
            "acc_epoch_time": 1620.4839441776276,
            "evaluate_time": 22.945228576660156,
            "loss": 0.8678708076477051
        },
        {
            "epoch": 30,
            "eval_acc": 0.8083818630318135,
            "forward_time": 25.711849689483643,
            "backward_time": 26.49430775642395,
            "cur_epoch_time": 52.206165075302124,
            "acc_epoch_time": 1672.6901092529297,
            "evaluate_time": 22.589232921600342,
            "loss": 0.8422507047653198
        },
        {
            "epoch": 31,
            "eval_acc": 0.815349795285202,
            "forward_time": 26.02682113647461,
            "backward_time": 26.8112735748291,
            "cur_epoch_time": 52.838101625442505,
            "acc_epoch_time": 1725.5282108783722,
            "evaluate_time": 22.79094910621643,
            "loss": 0.8217142820358276
        },
        {
            "epoch": 32,
            "eval_acc": 0.8208427637769244,
            "forward_time": 25.542561054229736,
            "backward_time": 26.51710820198059,
            "cur_epoch_time": 52.05967617034912,
            "acc_epoch_time": 1777.5878870487213,
            "evaluate_time": 22.543193340301514,
            "loss": 0.7969321608543396
        },
        {
            "epoch": 33,
            "eval_acc": 0.8248099076876129,
            "forward_time": 25.919570446014404,
            "backward_time": 26.659573793411255,
            "cur_epoch_time": 52.57915139198303,
            "acc_epoch_time": 1830.1670384407043,
            "evaluate_time": 22.86714506149292,
            "loss": 0.7774403095245361
        },
        {
            "epoch": 34,
            "eval_acc": 0.8292093685629276,
            "forward_time": 25.70600652694702,
            "backward_time": 26.329005241394043,
            "cur_epoch_time": 52.03502011299133,
            "acc_epoch_time": 1882.2020585536957,
            "evaluate_time": 23.73776936531067,
            "loss": 0.754805326461792
        },
        {
            "epoch": 35,
            "eval_acc": 0.8333036645220354,
            "forward_time": 26.07487201690674,
            "backward_time": 26.855474948883057,
            "cur_epoch_time": 52.930354595184326,
            "acc_epoch_time": 1935.13241314888,
            "evaluate_time": 22.723572731018066,
            "loss": 0.7349797487258911
        },
        {
            "epoch": 36,
            "eval_acc": 0.8370927955649365,
            "forward_time": 25.868483066558838,
            "backward_time": 26.994224548339844,
            "cur_epoch_time": 52.86271548271179,
            "acc_epoch_time": 1987.9951286315918,
            "evaluate_time": 22.697284936904907,
            "loss": 0.7149513363838196
        },
        {
            "epoch": 37,
            "eval_acc": 0.83978841899143,
            "forward_time": 25.657017707824707,
            "backward_time": 26.216586351394653,
            "cur_epoch_time": 51.87361121177673,
            "acc_epoch_time": 2039.8687398433685,
            "evaluate_time": 22.903626918792725,
            "loss": 0.6984219551086426
        },
        {
            "epoch": 38,
            "eval_acc": 0.8430689418406531,
            "forward_time": 26.71066951751709,
            "backward_time": 26.5186026096344,
            "cur_epoch_time": 53.229278326034546,
            "acc_epoch_time": 2093.098018169403,
            "evaluate_time": 22.727523803710938,
            "loss": 0.6823937892913818
        },
        {
            "epoch": 39,
            "eval_acc": 0.8453068178928362,
            "forward_time": 26.35703134536743,
            "backward_time": 26.69083046913147,
            "cur_epoch_time": 53.04788517951965,
            "acc_epoch_time": 2146.1459033489227,
            "evaluate_time": 22.9319109916687,
            "loss": 0.6688935160636902
        },
        {
            "epoch": 40,
            "eval_acc": 0.8480024413193297,
            "forward_time": 26.07402753829956,
            "backward_time": 26.271288633346558,
            "cur_epoch_time": 52.345356464385986,
            "acc_epoch_time": 2198.4912598133087,
            "evaluate_time": 23.001503229141235,
            "loss": 0.6527066826820374
        },
        {
            "epoch": 41,
            "eval_acc": 0.8500877349134095,
            "forward_time": 25.852473735809326,
            "backward_time": 26.78546690940857,
            "cur_epoch_time": 52.63794755935669,
            "acc_epoch_time": 2251.1292073726654,
            "evaluate_time": 23.045434951782227,
            "loss": 0.6425958275794983
        },
        {
            "epoch": 42,
            "eval_acc": 0.8519187244106503,
            "forward_time": 26.371269702911377,
            "backward_time": 26.547476053237915,
            "cur_epoch_time": 52.918750524520874,
            "acc_epoch_time": 2304.0479578971863,
            "evaluate_time": 23.114416122436523,
            "loss": 0.6298655271530151
        },
        {
            "epoch": 43,
            "eval_acc": 0.8546906390661954,
            "forward_time": 25.99640727043152,
            "backward_time": 27.734893083572388,
            "cur_epoch_time": 53.731308460235596,
            "acc_epoch_time": 2357.779266357422,
            "evaluate_time": 23.2588152885437,
            "loss": 0.6165210008621216
        },
        {
            "epoch": 44,
            "eval_acc": 0.8560893115988099,
            "forward_time": 26.194053411483765,
            "backward_time": 26.75254535675049,
            "cur_epoch_time": 52.94660568237305,
            "acc_epoch_time": 2410.725872039795,
            "evaluate_time": 23.1039879322052,
            "loss": 0.6065754890441895
        },
        {
            "epoch": 45,
            "eval_acc": 0.8577168578185794,
            "forward_time": 26.25554871559143,
            "backward_time": 26.840564489364624,
            "cur_epoch_time": 53.09612202644348,
            "acc_epoch_time": 2463.8219940662384,
            "evaluate_time": 23.60167646408081,
            "loss": 0.594933807849884
        },
        {
            "epoch": 46,
            "eval_acc": 0.8594715560867685,
            "forward_time": 26.379584789276123,
            "backward_time": 26.492973804473877,
            "cur_epoch_time": 52.87261366844177,
            "acc_epoch_time": 2516.69460773468,
            "evaluate_time": 22.959203004837036,
            "loss": 0.5865834355354309
        },
        {
            "epoch": 47,
            "eval_acc": 0.8605650637031762,
            "forward_time": 26.36117696762085,
            "backward_time": 26.72668218612671,
            "cur_epoch_time": 53.08786630630493,
            "acc_epoch_time": 2569.782474040985,
            "evaluate_time": 22.89189863204956,
            "loss": 0.5773078203201294
        },
        {
            "epoch": 48,
            "eval_acc": 0.8621926099229459,
            "forward_time": 26.09653329849243,
            "backward_time": 26.6792995929718,
            "cur_epoch_time": 52.775840282440186,
            "acc_epoch_time": 2622.5583143234253,
            "evaluate_time": 22.851718187332153,
            "loss": 0.5682553052902222
        },
        {
            "epoch": 49,
            "eval_acc": 0.8639981690105027,
            "forward_time": 26.083767890930176,
            "backward_time": 26.546095848083496,
            "cur_epoch_time": 52.629870653152466,
            "acc_epoch_time": 2675.1881849765778,
            "evaluate_time": 22.734987020492554,
            "loss": 0.5601739883422852
        },
        {
            "epoch": 50,
            "eval_acc": 0.8651425374462782,
            "forward_time": 26.169830560684204,
            "backward_time": 26.58316659927368,
            "cur_epoch_time": 52.75300407409668,
            "acc_epoch_time": 2727.9411890506744,
            "evaluate_time": 22.90131950378418,
            "loss": 0.5541217923164368
        },
        {
            "epoch": 51,
            "eval_acc": 0.8669226661241513,
            "forward_time": 26.22249436378479,
            "backward_time": 27.347881078720093,
            "cur_epoch_time": 53.57038331031799,
            "acc_epoch_time": 2781.5115723609924,
            "evaluate_time": 22.660337209701538,
            "loss": 0.5454710721969604
        },
        {
            "epoch": 52,
            "eval_acc": 0.8677110088243521,
            "forward_time": 26.206337451934814,
            "backward_time": 26.651271104812622,
            "cur_epoch_time": 52.85761499404907,
            "acc_epoch_time": 2834.3691873550415,
            "evaluate_time": 22.82090187072754,
            "loss": 0.53889399766922
        },
        {
            "epoch": 53,
            "eval_acc": 0.8688808076698116,
            "forward_time": 26.347386837005615,
            "backward_time": 26.400450706481934,
            "cur_epoch_time": 52.74784588813782,
            "acc_epoch_time": 2887.1170332431793,
            "evaluate_time": 23.060765743255615,
            "loss": 0.530491828918457
        },
        {
            "epoch": 54,
            "eval_acc": 0.8699997456959032,
            "forward_time": 26.6049861907959,
            "backward_time": 26.658215284347534,
            "cur_epoch_time": 53.2632532119751,
            "acc_epoch_time": 2940.3802864551544,
            "evaluate_time": 22.968440532684326,
            "loss": 0.5247589349746704
        },
        {
            "epoch": 55,
            "eval_acc": 0.871067822902627,
            "forward_time": 25.947131156921387,
            "backward_time": 26.382713556289673,
            "cur_epoch_time": 52.32985019683838,
            "acc_epoch_time": 2992.710136651993,
            "evaluate_time": 22.708220958709717,
            "loss": 0.518486499786377
        },
        {
            "epoch": 56,
            "eval_acc": 0.872339343386822,
            "forward_time": 26.612777709960938,
            "backward_time": 26.539433240890503,
            "cur_epoch_time": 53.152217626571655,
            "acc_epoch_time": 3045.8623542785645,
            "evaluate_time": 23.053560733795166,
            "loss": 0.5133987069129944
        },
        {
            "epoch": 57,
            "eval_acc": 0.8737125855097526,
            "forward_time": 26.19879698753357,
            "backward_time": 27.04713797569275,
            "cur_epoch_time": 53.24594330787659,
            "acc_epoch_time": 3099.108297586441,
            "evaluate_time": 22.981110334396362,
            "loss": 0.5071898698806763
        },
        {
            "epoch": 58,
            "eval_acc": 0.8750095364036314,
            "forward_time": 25.972209930419922,
            "backward_time": 26.7375807762146,
            "cur_epoch_time": 52.70979833602905,
            "acc_epoch_time": 3151.81809592247,
            "evaluate_time": 23.187439680099487,
            "loss": 0.5029211640357971
        },
        {
            "epoch": 59,
            "eval_acc": 0.8758741703328841,
            "forward_time": 25.835859060287476,
            "backward_time": 26.558161735534668,
            "cur_epoch_time": 52.39402914047241,
            "acc_epoch_time": 3204.2121250629425,
            "evaluate_time": 23.175512552261353,
            "loss": 0.49667322635650635
        },
        {
            "epoch": 60,
            "eval_acc": 0.8763573481168782,
            "forward_time": 27.592490434646606,
            "backward_time": 28.84477424621582,
            "cur_epoch_time": 56.43727231025696,
            "acc_epoch_time": 3260.6493973731995,
            "evaluate_time": 22.758975744247437,
            "loss": 0.49074432253837585
        },
        {
            "epoch": 61,
            "eval_acc": 0.8774508557332859,
            "forward_time": 26.614055156707764,
            "backward_time": 26.79994487762451,
            "cur_epoch_time": 53.41400671005249,
            "acc_epoch_time": 3314.063404083252,
            "evaluate_time": 22.747270584106445,
            "loss": 0.4873344898223877
        },
        {
            "epoch": 62,
            "eval_acc": 0.8781374767947512,
            "forward_time": 25.987816333770752,
            "backward_time": 26.657623052597046,
            "cur_epoch_time": 52.64544892311096,
            "acc_epoch_time": 3366.708853006363,
            "evaluate_time": 22.87532138824463,
            "loss": 0.4813899099826813
        },
        {
            "epoch": 63,
            "eval_acc": 0.8792564148208427,
            "forward_time": 25.57358431816101,
            "backward_time": 26.271047592163086,
            "cur_epoch_time": 51.844640016555786,
            "acc_epoch_time": 3418.5534930229187,
            "evaluate_time": 23.318989276885986,
            "loss": 0.47949981689453125
        },
        {
            "epoch": 64,
            "eval_acc": 0.8804770744856699,
            "forward_time": 27.156779289245605,
            "backward_time": 27.720558404922485,
            "cur_epoch_time": 54.877344846725464,
            "acc_epoch_time": 3473.430837869644,
            "evaluate_time": 23.041684865951538,
            "loss": 0.4729531705379486
        },
        {
            "epoch": 65,
            "eval_acc": 0.880960252269664,
            "forward_time": 27.058339595794678,
            "backward_time": 26.725242614746094,
            "cur_epoch_time": 53.78359627723694,
            "acc_epoch_time": 3527.214434146881,
            "evaluate_time": 23.209378957748413,
            "loss": 0.46932345628738403
        },
        {
            "epoch": 66,
            "eval_acc": 0.8820283294763879,
            "forward_time": 26.025442123413086,
            "backward_time": 27.89588475227356,
            "cur_epoch_time": 53.921382665634155,
            "acc_epoch_time": 3581.1358168125153,
            "evaluate_time": 23.1703839302063,
            "loss": 0.4658002257347107
        },
        {
            "epoch": 67,
            "eval_acc": 0.8820791902957557,
            "forward_time": 26.02900242805481,
            "backward_time": 26.52393388748169,
            "cur_epoch_time": 52.552945613861084,
            "acc_epoch_time": 3633.6887624263763,
            "evaluate_time": 22.715341567993164,
            "loss": 0.4625932276248932
        },
        {
            "epoch": 68,
            "eval_acc": 0.882486076850698,
            "forward_time": 26.386439561843872,
            "backward_time": 26.70486807823181,
            "cur_epoch_time": 53.09131479263306,
            "acc_epoch_time": 3686.7800772190094,
            "evaluate_time": 23.051244497299194,
            "loss": 0.45697471499443054
        },
        {
            "epoch": 69,
            "eval_acc": 0.8835795844671057,
            "forward_time": 27.099445104599,
            "backward_time": 26.703813314437866,
            "cur_epoch_time": 53.80326581001282,
            "acc_epoch_time": 3740.583343029022,
            "evaluate_time": 23.127206563949585,
            "loss": 0.4559601843357086
        },
        {
            "epoch": 70,
            "eval_acc": 0.8839356102026804,
            "forward_time": 25.84371066093445,
            "backward_time": 26.531547784805298,
            "cur_epoch_time": 52.37526488304138,
            "acc_epoch_time": 3792.9586079120636,
            "evaluate_time": 23.399153470993042,
            "loss": 0.44845861196517944
        },
        {
            "epoch": 71,
            "eval_acc": 0.8846222312641456,
            "forward_time": 27.602254390716553,
            "backward_time": 26.974977731704712,
            "cur_epoch_time": 54.57723879814148,
            "acc_epoch_time": 3847.535846710205,
            "evaluate_time": 22.67517876625061,
            "loss": 0.44707295298576355
        },
        {
            "epoch": 72,
            "eval_acc": 0.8847493833125651,
            "forward_time": 25.72676658630371,
            "backward_time": 26.10997748374939,
            "cur_epoch_time": 51.836751222610474,
            "acc_epoch_time": 3899.3725979328156,
            "evaluate_time": 24.37910532951355,
            "loss": 0.4422591030597687
        },
        {
            "epoch": 73,
            "eval_acc": 0.88556315642245,
            "forward_time": 26.860740423202515,
            "backward_time": 26.563905477523804,
            "cur_epoch_time": 53.424652338027954,
            "acc_epoch_time": 3952.7972502708435,
            "evaluate_time": 22.996058702468872,
            "loss": 0.4403882324695587
        },
        {
            "epoch": 74,
            "eval_acc": 0.8863260687129669,
            "forward_time": 26.194122552871704,
            "backward_time": 26.62280011177063,
            "cur_epoch_time": 52.816932678222656,
            "acc_epoch_time": 4005.614182949066,
            "evaluate_time": 22.824049711227417,
            "loss": 0.4358730912208557
        },
        {
            "epoch": 75,
            "eval_acc": 0.8868855377260128,
            "forward_time": 26.069027423858643,
            "backward_time": 26.413065195083618,
            "cur_epoch_time": 52.482102394104004,
            "acc_epoch_time": 4058.09628534317,
            "evaluate_time": 22.67156219482422,
            "loss": 0.432918906211853
        },
        {
            "epoch": 76,
            "eval_acc": 0.8869363985453805,
            "forward_time": 26.761589765548706,
            "backward_time": 27.183063983917236,
            "cur_epoch_time": 53.94466042518616,
            "acc_epoch_time": 4112.040945768356,
            "evaluate_time": 23.3747136592865,
            "loss": 0.42983391880989075
        },
        {
            "epoch": 77,
            "eval_acc": 0.8872161330519035,
            "forward_time": 27.248486280441284,
            "backward_time": 27.600934505462646,
            "cur_epoch_time": 54.849427700042725,
            "acc_epoch_time": 4166.890373468399,
            "evaluate_time": 23.530683755874634,
            "loss": 0.428610235452652
        },
        {
            "epoch": 78,
            "eval_acc": 0.8876993108358976,
            "forward_time": 25.76380443572998,
            "backward_time": 27.067654609680176,
            "cur_epoch_time": 52.83146595954895,
            "acc_epoch_time": 4219.721839427948,
            "evaluate_time": 23.5537588596344,
            "loss": 0.4246264100074768
        },
        {
            "epoch": 79,
            "eval_acc": 0.8880044757521044,
            "forward_time": 26.386052131652832,
            "backward_time": 26.624722719192505,
            "cur_epoch_time": 53.01078200340271,
            "acc_epoch_time": 4272.732621431351,
            "evaluate_time": 23.13977551460266,
            "loss": 0.4221992492675781
        },
        {
            "epoch": 80,
            "eval_acc": 0.8885130839457823,
            "forward_time": 27.32368540763855,
            "backward_time": 26.494995832443237,
            "cur_epoch_time": 53.818687915802,
            "acc_epoch_time": 4326.551309347153,
            "evaluate_time": 23.260080814361572,
            "loss": 0.41878584027290344
        },
        {
            "epoch": 81,
            "eval_acc": 0.8889962617297764,
            "forward_time": 26.199727058410645,
            "backward_time": 26.441112995147705,
            "cur_epoch_time": 52.6408474445343,
            "acc_epoch_time": 4379.192156791687,
            "evaluate_time": 22.493252277374268,
            "loss": 0.41622471809387207
        },
        {
            "epoch": 82,
            "eval_acc": 0.8895303003331384,
            "forward_time": 25.977943897247314,
            "backward_time": 26.199162244796753,
            "cur_epoch_time": 52.17711281776428,
            "acc_epoch_time": 4431.369269609451,
            "evaluate_time": 22.752087354660034,
            "loss": 0.4142700731754303
        },
        {
            "epoch": 83,
            "eval_acc": 0.8895557307428222,
            "forward_time": 25.989229202270508,
            "backward_time": 26.186041831970215,
            "cur_epoch_time": 52.175278425216675,
            "acc_epoch_time": 4483.544548034668,
            "evaluate_time": 23.039276361465454,
            "loss": 0.410571426153183
        },
        {
            "epoch": 84,
            "eval_acc": 0.8903949342623909,
            "forward_time": 26.56443762779236,
            "backward_time": 26.308302879333496,
            "cur_epoch_time": 52.87274742126465,
            "acc_epoch_time": 4536.417295455933,
            "evaluate_time": 22.82071042060852,
            "loss": 0.40935251116752625
        },
        {
            "epoch": 85,
            "eval_acc": 0.8905983775398622,
            "forward_time": 25.799073219299316,
            "backward_time": 26.095757246017456,
            "cur_epoch_time": 51.89483714103699,
            "acc_epoch_time": 4588.31213259697,
            "evaluate_time": 23.282952785491943,
            "loss": 0.4092610478401184
        },
        {
            "epoch": 86,
            "eval_acc": 0.8909798336851207,
            "forward_time": 27.701613426208496,
            "backward_time": 26.856879949569702,
            "cur_epoch_time": 54.558499813079834,
            "acc_epoch_time": 4642.870632410049,
            "evaluate_time": 23.106384754180908,
            "loss": 0.40380948781967163
        },
        {
            "epoch": 87,
            "eval_acc": 0.8907255295882817,
            "forward_time": 26.378066778182983,
            "backward_time": 26.879955530166626,
            "cur_epoch_time": 53.25802946090698,
            "acc_epoch_time": 4696.128661870956,
            "evaluate_time": 23.11904811859131,
            "loss": 0.40260058641433716
        },
        {
            "epoch": 88,
            "eval_acc": 0.8913358594206953,
            "forward_time": 26.23990511894226,
            "backward_time": 26.838192462921143,
            "cur_epoch_time": 53.07810378074646,
            "acc_epoch_time": 4749.206765651703,
            "evaluate_time": 22.659194707870483,
            "loss": 0.40053263306617737
        },
        {
            "epoch": 89,
            "eval_acc": 0.8915138722884826,
            "forward_time": 25.49955940246582,
            "backward_time": 26.314249277114868,
            "cur_epoch_time": 51.81381368637085,
            "acc_epoch_time": 4801.020579338074,
            "evaluate_time": 22.50050711631775,
            "loss": 0.39845940470695496
        },
        {
            "epoch": 90,
            "eval_acc": 0.8921496325305801,
            "forward_time": 26.224285364151,
            "backward_time": 26.168357610702515,
            "cur_epoch_time": 52.39264965057373,
            "acc_epoch_time": 4853.4132289886475,
            "evaluate_time": 22.587578058242798,
            "loss": 0.3963123857975006
        },
        {
            "epoch": 91,
            "eval_acc": 0.8925310886758385,
            "forward_time": 26.816603660583496,
            "backward_time": 26.295682191848755,
            "cur_epoch_time": 53.112293004989624,
            "acc_epoch_time": 4906.525521993637,
            "evaluate_time": 22.63905119895935,
            "loss": 0.3934663236141205
        },
        {
            "epoch": 92,
            "eval_acc": 0.892912544821097,
            "forward_time": 26.525529146194458,
            "backward_time": 26.587672472000122,
            "cur_epoch_time": 53.11320734024048,
            "acc_epoch_time": 4959.638729333878,
            "evaluate_time": 22.5254487991333,
            "loss": 0.3938169479370117
        },
        {
            "epoch": 93,
            "eval_acc": 0.8931159880985683,
            "forward_time": 26.664534330368042,
            "backward_time": 27.14194631576538,
            "cur_epoch_time": 53.806488037109375,
            "acc_epoch_time": 5013.445217370987,
            "evaluate_time": 23.237946271896362,
            "loss": 0.3900529742240906
        },
        {
            "epoch": 94,
            "eval_acc": 0.8937263179309819,
            "forward_time": 26.45364236831665,
            "backward_time": 26.173361778259277,
            "cur_epoch_time": 52.6270112991333,
            "acc_epoch_time": 5066.07222867012,
            "evaluate_time": 22.586355447769165,
            "loss": 0.38693779706954956
        },
        {
            "epoch": 95,
            "eval_acc": 0.8938534699794014,
            "forward_time": 25.56783366203308,
            "backward_time": 27.05127263069153,
            "cur_epoch_time": 52.61911344528198,
            "acc_epoch_time": 5118.691342115402,
            "evaluate_time": 22.583329439163208,
            "loss": 0.387009859085083
        },
        {
            "epoch": 96,
            "eval_acc": 0.8940060524375048,
            "forward_time": 26.22214984893799,
            "backward_time": 27.223037242889404,
            "cur_epoch_time": 53.44519400596619,
            "acc_epoch_time": 5172.136536121368,
            "evaluate_time": 23.08710503578186,
            "loss": 0.38460925221443176
        },
        {
            "epoch": 97,
            "eval_acc": 0.8946418126796023,
            "forward_time": 25.590007305145264,
            "backward_time": 28.31646728515625,
            "cur_epoch_time": 53.90648150444031,
            "acc_epoch_time": 5226.043017625809,
            "evaluate_time": 22.765124082565308,
            "loss": 0.38171789050102234
        },
        {
            "epoch": 98,
            "eval_acc": 0.8951504208732802,
            "forward_time": 26.364415407180786,
            "backward_time": 26.36870789527893,
            "cur_epoch_time": 52.73312997817993,
            "acc_epoch_time": 5278.776147603989,
            "evaluate_time": 22.974199295043945,
            "loss": 0.38062116503715515
        },
        {
            "epoch": 99,
            "eval_acc": 0.89573532029601,
            "forward_time": 26.099852323532104,
            "backward_time": 26.11817741394043,
            "cur_epoch_time": 52.21803665161133,
            "acc_epoch_time": 5330.9941842556,
            "evaluate_time": 22.84592318534851,
            "loss": 0.3782913386821747
        }
    ]
}