{
    "version": 1,
    "graph_name": "reddit",
    "train_mode": "minibatch",
    "num_node": 232965,
    "num_edge": 114848857,
    "cpu_model": "Intel(R) Xeon(R) Gold 6240 CPU @ 2.60GHz",
    "feat_width": 602,
    "batch_size": 1024,
    "fanouts": [
        4,
        4
    ],
    "num_epoch": 30,
    "num_partition": 1,
    "weight_decay": 0.0,
    "learning_rate": 0.001,
    "dropout": 0.3,
    "test_acc": 0.05572410672903061,
    "results": [
        {
            "epoch": 0,
            "eval_acc": 0.002769501879811287,
            "sample_time": 2.047980785369873,
            "load_time": 0.8373289108276367,
            "forward_time": 5.347109079360962,
            "backward_time": 3.2390871047973633,
            "cur_epoch_time": 11.471962690353394,
            "acc_epoch_time": 11.471962690353394,
            "evaluate_time": 78.975900888443,
            "loss": 2.7530100345611572
        },
        {
            "epoch": 1,
            "eval_acc": 0.058411311358213425,
            "sample_time": 1.953517198562622,
            "load_time": 0.7641222476959229,
            "forward_time": 4.729127645492554,
            "backward_time": 3.1190896034240723,
            "cur_epoch_time": 10.56635069847107,
            "acc_epoch_time": 22.038313388824463,
            "evaluate_time": 76.14404654502869,
            "loss": 0.7844036817550659
        },
        {
            "epoch": 2,
            "eval_acc": 0.05836934968829155,
            "sample_time": 1.912529706954956,
            "load_time": 0.6252033710479736,
            "forward_time": 4.734328031539917,
            "backward_time": 3.4064419269561768,
            "cur_epoch_time": 10.678997993469238,
            "acc_epoch_time": 32.7173113822937,
            "evaluate_time": 80.00362086296082,
            "loss": 0.8991413712501526
        },
        {
            "epoch": 3,
            "eval_acc": 0.05857916176319122,
            "sample_time": 1.9908788204193115,
            "load_time": 0.65572190284729,
            "forward_time": 4.415870904922485,
            "backward_time": 2.872436046600342,
            "cur_epoch_time": 9.935392379760742,
            "acc_epoch_time": 42.65270376205444,
            "evaluate_time": 74.66739988327026,
            "loss": 0.8104870915412903
        },
        {
            "epoch": 4,
            "eval_acc": 0.05836934968829155,
            "sample_time": 1.9375274181365967,
            "load_time": 0.7478501796722412,
            "forward_time": 4.551045179367065,
            "backward_time": 3.083791494369507,
            "cur_epoch_time": 10.320687532424927,
            "acc_epoch_time": 52.97339129447937,
            "evaluate_time": 79.72823667526245,
            "loss": 0.9288226962089539
        },
        {
            "epoch": 5,
            "eval_acc": 0.05853720009326935,
            "sample_time": 1.9657371044158936,
            "load_time": 0.7564218044281006,
            "forward_time": 4.462839841842651,
            "backward_time": 3.279676914215088,
            "cur_epoch_time": 10.465171575546265,
            "acc_epoch_time": 63.438562870025635,
            "evaluate_time": 80.56675243377686,
            "loss": 0.8083888292312622
        },
        {
            "epoch": 6,
            "eval_acc": 0.05950232967734337,
            "sample_time": 1.9613287448883057,
            "load_time": 0.5922122001647949,
            "forward_time": 4.500091552734375,
            "backward_time": 2.9038712978363037,
            "cur_epoch_time": 9.957968711853027,
            "acc_epoch_time": 73.39653158187866,
            "evaluate_time": 79.30913257598877,
            "loss": 0.7913609743118286
        },
        {
            "epoch": 7,
            "eval_acc": 0.06118081510066986,
            "sample_time": 2.0187597274780273,
            "load_time": 1.020465612411499,
            "forward_time": 4.792443037033081,
            "backward_time": 3.4124467372894287,
            "cur_epoch_time": 11.244592189788818,
            "acc_epoch_time": 84.64112377166748,
            "evaluate_time": 80.95523810386658,
            "loss": 0.8872694373130798
        },
        {
            "epoch": 8,
            "eval_acc": 0.05979606509208679,
            "sample_time": 1.9253861904144287,
            "load_time": 0.9392850399017334,
            "forward_time": 4.628378391265869,
            "backward_time": 3.3659508228302,
            "cur_epoch_time": 10.859492540359497,
            "acc_epoch_time": 95.50061631202698,
            "evaluate_time": 78.18072414398193,
            "loss": 0.8209912180900574
        },
        {
            "epoch": 9,
            "eval_acc": 0.004238177090883255,
            "sample_time": 1.9780302047729492,
            "load_time": 0.7677872180938721,
            "forward_time": 4.471156358718872,
            "backward_time": 3.0956387519836426,
            "cur_epoch_time": 10.313082933425903,
            "acc_epoch_time": 105.81369924545288,
            "evaluate_time": 80.39934825897217,
            "loss": 0.8065769672393799
        },
        {
            "epoch": 10,
            "eval_acc": 0.0586211234331131,
            "sample_time": 1.9060659408569336,
            "load_time": 0.7373828887939453,
            "forward_time": 4.734900712966919,
            "backward_time": 3.113826036453247,
            "cur_epoch_time": 10.492628574371338,
            "acc_epoch_time": 116.30632781982422,
            "evaluate_time": 79.47446322441101,
            "loss": 0.7755149006843567
        },
        {
            "epoch": 11,
            "eval_acc": 0.05568377301096916,
            "sample_time": 1.9685733318328857,
            "load_time": 0.6225521564483643,
            "forward_time": 4.493072032928467,
            "backward_time": 2.9802894592285156,
            "cur_epoch_time": 10.064959526062012,
            "acc_epoch_time": 126.37128734588623,
            "evaluate_time": 78.73854613304138,
            "loss": 0.7927489280700684
        },
        {
            "epoch": 12,
            "eval_acc": 0.0011329780099913478,
            "sample_time": 1.9173619747161865,
            "load_time": 0.5333027839660645,
            "forward_time": 4.4062511920928955,
            "backward_time": 2.795344829559326,
            "cur_epoch_time": 9.652718544006348,
            "acc_epoch_time": 136.02400588989258,
            "evaluate_time": 79.40130805969238,
            "loss": 0.7618984580039978
        },
        {
            "epoch": 13,
            "eval_acc": 0.05874700844287872,
            "sample_time": 1.9159529209136963,
            "load_time": 0.5373721122741699,
            "forward_time": 4.3196258544921875,
            "backward_time": 2.8177969455718994,
            "cur_epoch_time": 9.591196060180664,
            "acc_epoch_time": 145.61520195007324,
            "evaluate_time": 80.07189965248108,
            "loss": 0.75629061460495
        },
        {
            "epoch": 14,
            "eval_acc": 0.05857916176319122,
            "sample_time": 1.9642949104309082,
            "load_time": 0.5297508239746094,
            "forward_time": 4.584635496139526,
            "backward_time": 3.1086525917053223,
            "cur_epoch_time": 10.187811851501465,
            "acc_epoch_time": 155.8030138015747,
            "evaluate_time": 79.44036722183228,
            "loss": 0.8082730770111084
        },
        {
            "epoch": 15,
            "eval_acc": 0.05849523842334747,
            "sample_time": 1.947681188583374,
            "load_time": 0.7421822547912598,
            "forward_time": 4.574495077133179,
            "backward_time": 3.136462688446045,
            "cur_epoch_time": 10.401310443878174,
            "acc_epoch_time": 166.20432424545288,
            "evaluate_time": 81.3384370803833,
            "loss": 0.8216366171836853
        },
        {
            "epoch": 16,
            "eval_acc": 0.05887289717793465,
            "sample_time": 1.8297898769378662,
            "load_time": 0.5546793937683105,
            "forward_time": 4.48745584487915,
            "backward_time": 2.833594799041748,
            "cur_epoch_time": 9.705989360809326,
            "acc_epoch_time": 175.9103136062622,
            "evaluate_time": 79.77513194084167,
            "loss": 0.8378358483314514
        },
        {
            "epoch": 17,
            "eval_acc": 0.05866308510303497,
            "sample_time": 2.013834238052368,
            "load_time": 0.7264454364776611,
            "forward_time": 4.421186685562134,
            "backward_time": 3.036560297012329,
            "cur_epoch_time": 10.19849181175232,
            "acc_epoch_time": 186.10880541801453,
            "evaluate_time": 80.15540623664856,
            "loss": 0.8628641963005066
        },
        {
            "epoch": 18,
            "eval_acc": 0.038143593817949295,
            "sample_time": 2.0019633769989014,
            "load_time": 0.5704505443572998,
            "forward_time": 4.35817289352417,
            "backward_time": 2.9484455585479736,
            "cur_epoch_time": 9.879485368728638,
            "acc_epoch_time": 195.98829078674316,
            "evaluate_time": 79.30154871940613,
            "loss": 0.7115978598594666
        },
        {
            "epoch": 19,
            "eval_acc": 0.0586211234331131,
            "sample_time": 1.960573673248291,
            "load_time": 0.6236879825592041,
            "forward_time": 4.557702541351318,
            "backward_time": 2.956357955932617,
            "cur_epoch_time": 10.098791122436523,
            "acc_epoch_time": 206.0870819091797,
            "evaluate_time": 80.1120765209198,
            "loss": 0.8317660093307495
        },
        {
            "epoch": 20,
            "eval_acc": 0.0010490537388250232,
            "sample_time": 1.9758455753326416,
            "load_time": 0.6619234085083008,
            "forward_time": 4.554774284362793,
            "backward_time": 2.9268105030059814,
            "cur_epoch_time": 10.119808912277222,
            "acc_epoch_time": 216.2068908214569,
            "evaluate_time": 79.91923809051514,
            "loss": 0.8397052884101868
        },
        {
            "epoch": 21,
            "eval_acc": 0.0010490537388250232,
            "sample_time": 2.0415663719177246,
            "load_time": 0.6326026916503906,
            "forward_time": 4.620917558670044,
            "backward_time": 3.185304641723633,
            "cur_epoch_time": 10.480859518051147,
            "acc_epoch_time": 226.68775033950806,
            "evaluate_time": 77.3359682559967,
            "loss": 0.8183132410049438
        },
        {
            "epoch": 22,
            "eval_acc": 0.0027275397442281246,
            "sample_time": 1.9374122619628906,
            "load_time": 0.5791208744049072,
            "forward_time": 4.522165775299072,
            "backward_time": 3.048525810241699,
            "cur_epoch_time": 10.087706804275513,
            "acc_epoch_time": 236.77545714378357,
            "evaluate_time": 80.38007354736328,
            "loss": 0.8337757587432861
        },
        {
            "epoch": 23,
            "eval_acc": 0.0009231673320755363,
            "sample_time": 1.929741621017456,
            "load_time": 0.5641078948974609,
            "forward_time": 4.254884958267212,
            "backward_time": 2.8663134574890137,
            "cur_epoch_time": 9.615540027618408,
            "acc_epoch_time": 246.39099717140198,
            "evaluate_time": 78.88913226127625,
            "loss": 0.833064615726471
        },
        {
            "epoch": 24,
            "eval_acc": 0.05866308510303497,
            "sample_time": 1.9742584228515625,
            "load_time": 0.8001863956451416,
            "forward_time": 4.4916627407073975,
            "backward_time": 3.313105583190918,
            "cur_epoch_time": 10.579704523086548,
            "acc_epoch_time": 256.9707016944885,
            "evaluate_time": 81.1870551109314,
            "loss": 0.8295251131057739
        },
        {
            "epoch": 25,
            "eval_acc": 0.0006294322665780783,
            "sample_time": 1.992286205291748,
            "load_time": 0.7547078132629395,
            "forward_time": 4.536754846572876,
            "backward_time": 3.1436848640441895,
            "cur_epoch_time": 10.42790150642395,
            "acc_epoch_time": 267.3986032009125,
            "evaluate_time": 78.59645342826843,
            "loss": 0.770537257194519
        },
        {
            "epoch": 26,
            "eval_acc": 0.0010070916032418609,
            "sample_time": 1.980370044708252,
            "load_time": 0.5130901336669922,
            "forward_time": 4.0725743770599365,
            "backward_time": 2.9450321197509766,
            "cur_epoch_time": 9.511559247970581,
            "acc_epoch_time": 276.91016244888306,
            "evaluate_time": 80.6318109035492,
            "loss": 0.781887412071228
        },
        {
            "epoch": 27,
            "eval_acc": 0.058327388018369675,
            "sample_time": 1.8610754013061523,
            "load_time": 0.9828357696533203,
            "forward_time": 4.411517381668091,
            "backward_time": 3.15118408203125,
            "cur_epoch_time": 10.407092809677124,
            "acc_epoch_time": 287.3172552585602,
            "evaluate_time": 80.59093594551086,
            "loss": 0.7185750603675842
        },
        {
            "epoch": 28,
            "eval_acc": 0.052830345928668976,
            "sample_time": 1.9568676948547363,
            "load_time": 0.6813087463378906,
            "forward_time": 4.88824725151062,
            "backward_time": 3.4550368785858154,
            "cur_epoch_time": 10.981951236724854,
            "acc_epoch_time": 298.29920649528503,
            "evaluate_time": 80.41499304771423,
            "loss": 0.7551983594894409
        },
        {
            "epoch": 29,
            "eval_acc": 0.057446181774139404,
            "sample_time": 1.8809735774993896,
            "load_time": 0.8232095241546631,
            "forward_time": 4.74503493309021,
            "backward_time": 3.2988474369049072,
            "cur_epoch_time": 10.74854040145874,
            "acc_epoch_time": 309.0477468967438,
            "evaluate_time": 80.33849740028381,
            "loss": 0.7241358160972595
        }
    ]
}